quick_password/__init__.py
quick_password/generate_password.py
quick_password-0.2.dist-info/METADATA
quick_password-0.2.dist-info/WHEEL
quick_password-0.2.dist-info/top_level.txt
quick_password-0.2.dist-info/RECORD
